AUTHORS
CHANGELOG.rst
LICENSE
MANIFEST.in
README
README.rst
requirements.txt
setup.cfg
setup.py
docs/CHANGELOG.rst
docs/CONTRIBUTING.rst
docs/LICENSE.rst
docs/README.rst
docs/conf.py
docs/index.rst
docs/html/index.html
sum_walker/__init__.py
sum_walker/__main__.py
sum_walker/iterator_wrapper.py
sum_walker/template.py
sum_walker.egg-info/PKG-INFO
sum_walker.egg-info/SOURCES.txt
sum_walker.egg-info/dependency_links.txt
sum_walker.egg-info/not-zip-safe
sum_walker.egg-info/top_level.txt
tests/__init__.py
tests/test_sanity.py
tests/test_sum_walker.py