Metadata-Version: 1.1
Name: sum-walker
Version: 0.8.2
Summary: Iterate over sums of a certain number of elements
Home-page: https://github.com/shlomif/sum_walker
Author: Shlomi Fish
Author-email: shlomif@cpan.org
License: 3-clause BSD
Keywords: sum_walker
Platform: any
Classifier: Development Status :: 1 - Planning
Classifier: Programming Language :: Python
Classifier: Programming Language :: Python :: 3
Classifier: Programming Language :: Python :: 3.5
Classifier: Programming Language :: Python :: 3.6
Classifier: Programming Language :: Python :: 3.7
Classifier: Programming Language :: Python :: 3.8
